[
    {
        "Name": "Name",
        "Category": "Personal",
        "Pattern": [
            "^.*(firstname|fname|lastname|lname|fullname|fname).*$",
            "^.*(vorname|vname|nachname|nname|vollstandigername|vollname).*$"
        ]
    },
    {
        "Name": "Address",
        "Category": "Location",
        "Pattern": [
            "^.*address.*$",
            "^.*adresse.*$"
        ]
    },
    {
        "Name": "City",
        "Category": "Location",
        "Pattern": [
            "^.*city.*$",
            "^.*stadt.*$"
        ]
    },
    {
        "Name": "State",
        "Category": "Location",
        "Pattern": [
            "^.*state.*$",
            "^.*provinz.*$"
        ]
    },
    {
        "Name": "Zipcode",
        "Category": "Location",
        "Pattern": [
            "^.*zip.*$",
            "^.*postleitzahl.*$"
        ]
    },
    {
        "Name": "County",
        "Category": "Location",
        "Pattern": [
            "^.*county.*$",
            "^.*bezirk.*$"
        ]
    },
    {
        "Name": "Country",
        "Category": "Location",
        "Pattern": [
            "^.*country.*$",
            "^.*land.*$"
        ]
    },
    {
        "Name": "E-mail",
        "Category": "Communication",
        "Pattern": [
            "^.*(email|e-mail|mail).*$"
        ]
    },
    {
        "Name": "IPAddres",
        "Category": "System",
        "Pattern": [
            "^.*(ip|ipaddress|ipv4|ipv6).*$"
        ]
    },
    {
        "Name": "Username",
        "Category": "Security",
        "Pattern": [
            "^.*(userid|username).*$",
            "^.*(nutzerid|nutzername).*$"
        ]
    },
    {
        "Name": "Password",
        "Category": "Communication",
        "Pattern": [
            "^.*pass.*$"
        ]
    }
]